moonpythonlib/__init__.py
moonpythonlib/myfunctions.py
moonpythonlib-0.1.5.dist-info/METADATA
moonpythonlib-0.1.5.dist-info/WHEEL
moonpythonlib-0.1.5.dist-info/top_level.txt
moonpythonlib-0.1.5.dist-info/RECORD
