Metadata-Version: 2.1
Name: moonpythonlib
Version: 0.1.5
Summary: Dependency Confusion Attack POC
Home-page: UNKNOWN
Author: Me
License: MIT
Platform: UNKNOWN
